sqliteoop/__init__.py
sqliteoop/sqlite.py
sqlite_oop-0.0.3.dist-info/LICENSE
sqlite_oop-0.0.3.dist-info/METADATA
sqlite_oop-0.0.3.dist-info/WHEEL
sqlite_oop-0.0.3.dist-info/top_level.txt
sqlite_oop-0.0.3.dist-info/RECORD
