Metadata-Version: 2.1
Name: sqlite-oop
Version: 0.0.3
Summary: python sqlite OOP class
Home-page: https://github.com/hahadu/sqlite-py-oop
Author: hahadu
Author-email: mhyzhu@163.com
License: UNKNOWN
Project-URL: Bug Tracker, https://github.com/hahadu/sqlite-py-oop/issues
Platform: UNKNOWN
Classifier: Programming Language :: Python :: 3
Classifier: License :: OSI Approved :: MIT License
Classifier: Operating System :: OS Independent
Requires-Python: >=3.6
License-File: LICENSE
